setup.py
GaussianBinomial_dist.egg-info/PKG-INFO
GaussianBinomial_dist.egg-info/SOURCES.txt
GaussianBinomial_dist.egg-info/dependency_links.txt
GaussianBinomial_dist.egg-info/not-zip-safe
GaussianBinomial_dist.egg-info/top_level.txt
distributions/Binomialdistribution.py
distributions/Gaussiandistribution.py
distributions/Generaldistribution.py
distributions/__init__.py