Metadata-Version: 1.0
Name: GaussianBinomial-dist
Version: 0.1
Summary: Gaussian and Binomial distributions
Home-page: UNKNOWN
Author: Rahul Sunil
Author-email: rahulsunil2@gmail.com
License: UNKNOWN
Platform: UNKNOWN
